reddit_usernames/__init__.py
reddit_usernames/reddit_session.py
reddit_usernames-0.1.dist-info/LICENSE.md
reddit_usernames-0.1.dist-info/METADATA
reddit_usernames-0.1.dist-info/WHEEL
reddit_usernames-0.1.dist-info/top_level.txt
reddit_usernames-0.1.dist-info/RECORD
