Metadata-Version: 2.1
Name: reddit-usernames
Version: 0.1
Summary: Library for finding free usernames on reddit
Home-page: http://github.com/yoavravid/RedditUsernames
Author: Yoav Ravid
Author-email: yravid@gmail.com
License: MIT
Platform: UNKNOWN
Requires-Dist: bs4
Requires-Dist: requests
